<?xml version="1.0" encoding="utf-8" ?>
<Network>
  <CountOfLayers>4</CountOfLayers>
  <TrainingSetCount>1000</TrainingSetCount>
  <Layers>
    <Layer>
      <Pretrain>true</Pretrain>
      <RbmConfig>
        <TrainingAlgorithm>Hinton</TrainingAlgorithm>
        <CountOfEpoches>100</CountOfEpoches>
        <Alpha>0.01 </Alpha>
        <KParameter>2</KParameter>
        <LoggingEnabled>true</LoggingEnabled>
        <InputDataType>Binary</InputDataType>
      </RbmConfig>
      <ActivationFunction>Sigmoidal</ActivationFunction>
      <NeuronsCount>1000</NeuronsCount>
      <WeightsCount>841</WeightsCount>
      <IsBinary>false</IsBinary>
      <Alpha>0.01</Alpha>
    </Layer>
    <Layer>
      <Pretrain>true</Pretrain>
      <RbmConfig>
        <TrainingAlgorithm>Hinton</TrainingAlgorithm>
        <CountOfEpoches>100</CountOfEpoches>
        <Alpha>0.01 </Alpha>
        <KParameter>2</KParameter>
        <LoggingEnabled>true</LoggingEnabled>
        <InputDataType>Binary</InputDataType>
      </RbmConfig>
      <ActivationFunction>Sigmoidal</ActivationFunction>
      <NeuronsCount>500</NeuronsCount>
      <WeightsCount>1000</WeightsCount>
      <IsBinary>false</IsBinary>
    </Layer >
    <Layer>
      <Pretrain>true</Pretrain>
      <RbmConfig>
        <TrainingAlgorithm>Hinton</TrainingAlgorithm>
        <CountOfEpoches>100</CountOfEpoches>
        <Alpha>0.01 </Alpha>
        <KParameter>2</KParameter>
        <LoggingEnabled>true</LoggingEnabled>
        <InputDataType>Binary</InputDataType>
      </RbmConfig>
      <ActivationFunction>Sigmoidal</ActivationFunction>
      <NeuronsCount>256</NeuronsCount>
      <WeightsCount>500</WeightsCount>
      <IsBinary>false</IsBinary>
    </Layer>
    <Layer>
      <Pretrain>false</Pretrain>
      <ActivationFunction>Softmax</ActivationFunction>
      <NeuronsCount>2</NeuronsCount>
      <WeightsCount>256</WeightsCount>
      <IsBinary>false</IsBinary>
    </Layer>
  </Layers>
</Network>